pghist_client/__init__.py
pghist_client/enums.py
pghist_client/utils.py
pghist_client/pghist_rest/__init__.py
pghist_client/pghist_rest/backend.py
pghist_client/pghist_rest/constants.py
pghist_client/pghist_rest/dataclasses.py
pghist_client/pghist_rest/server.py
pghist_client/pghist_rest/utils.py
pghist_client-0.1.2.dist-info/LICENSE
pghist_client-0.1.2.dist-info/METADATA
pghist_client-0.1.2.dist-info/WHEEL
pghist_client-0.1.2.dist-info/top_level.txt
pghist_client-0.1.2.dist-info/RECORD
