Metadata-Version: 2.1
Name: pghist-client
Version: 0.1.2
Summary: Клиент для взаимодействия с сервисом логирования действий пользователя (PGHist).
Home-page: https://stash.bars-open.ru/projects/M3/repos/pghist-client
Author: BARS Group
Author-email: bars@bars.group
License: MIT
Keywords: django pghist client
Classifier: Development Status :: 4 - Beta
Classifier: Environment :: Web Environment
Classifier: Intended Audience :: Developers
Classifier: Natural Language :: Russian
Classifier: Programming Language :: Python :: 3.9
Classifier: Topic :: Software Development :: Libraries
Classifier: Topic :: Utilities
License-File: LICENSE
Requires-Dist: requests <3,>=2
Requires-Dist: requests-oauthlib <=1.3.1
Requires-Dist: oauthlib <3.3,>=2
Requires-Dist: Django <5.1,>=2.2
Requires-Dist: djangorestframework
